{
    "openapi": "3.0.2",
    "info": {
        "title": "Launcher Local Server",
        "version": "0.1"
    },
    "servers": [
        {
            "url": "http://localhost/v0"
        }
    ],
    "paths": {
        "/ping": {
            "get": {
                "description": "",
                "parameters": [],
                "responses": {
                    "200": {
                        "description": "PONG"
                    }
                }
            }
        },
        "/": {
            "get": {
                "responses": {
                    "404": {
                        "description": "Nothing Here"
                    }
                }
            }
        },
        "/id": {
            "get": {
                "responses": {
                    "200": {
                        "description": "data",
                        "content": {
                            "application/octet-stream": {
                                "schema": {
                                    "type": "string",
                                    "format": "binary"
                                }
                            }
                        }
                    }
                }
            }
        }
    }
}